stash_mcp_server/__init__.py
stash_mcp_server/main.py
stash_mcp_server-0.1.3.dist-info/METADATA
stash_mcp_server-0.1.3.dist-info/WHEEL
stash_mcp_server-0.1.3.dist-info/entry_points.txt
stash_mcp_server-0.1.3.dist-info/RECORD
