Metadata-Version: 2.4
Name: stash-mcp-server
Version: 0.1.3
Summary: Stash MCP Server for issue analysis and task management
Project-URL: Homepage, https://github.com/lambersonistaken/stash-mcp-server
Project-URL: Repository, https://github.com/lambersonistaken/stash-mcp-server
Project-URL: Documentation, https://github.com/lambersonistaken/stash-mcp-server#readme
Project-URL: Issues, https://github.com/lambersonistaken/stash-mcp-server/issues
Author-email: Lamberson <lambersonistaken@gmail.com>
Maintainer-email: Lamberson <lambersonistaken@gmail.com>
License: MIT
Keywords: issue-analysis,mcp,stash,task-management
Classifier: Development Status :: 4 - Beta
Classifier: Intended Audience :: Developers
Classifier: License :: OSI Approved :: MIT License
Classifier: Programming Language :: Python :: 3
Classifier: Programming Language :: Python :: 3.12
Classifier: Topic :: Software Development :: Libraries :: Python Modules
Requires-Python: >=3.12
Requires-Dist: httpx>=0.25.0
Requires-Dist: mcp>=1.13.0
Requires-Dist: pydantic-settings>=2.0.0
Requires-Dist: python-dotenv>=1.0.0
